{
  "gitSyncId": "65f32f6e703438070835cba7_65f3432b703438070835cbfb",
  "id": "Endpoints_UpdateQuery",
  "pluginId": "postgres-plugin",
  "pluginType": "DB",
  "unpublishedAction": {
    "actionConfiguration": {
      "body": "UPDATE tas_gateway_core.\"tch_endpoints\" SET\n\t\t\"url\" = '{{update_form.fieldState.url.isVisible ? update_form.formData.url : update_form.sourceData.url}}',\n\t\t\"description\" = '{{update_form.fieldState.description.isVisible ? update_form.formData.description : update_form.sourceData.description}}'\nWHERE \"id\" = {{data_table.selectedRow.id}};",
      "encodeParamsToggle": true,
      "paginationType": "NONE",
      "pluginSpecifiedTemplates": [
        {
          "value": true
        }
      ],
      "timeoutInMillisecond": 10000
    },
    "confirmBeforeExecute": false,
    "datasource": {
      "id": "tgw_db_dev",
      "isAutoGenerated": false,
      "name": "tgw_db_dev",
      "pluginId": "postgres-plugin"
    },
    "dynamicBindingPathList": [],
    "executeOnLoad": false,
    "name": "UpdateQuery",
    "pageId": "Endpoints",
    "userSetOnLoad": false
  }
}